cpf_generator/CPF.py
cpf_generator/__init__.py
cpf_generator-2.1.4.dist-info/LICENSE.md
cpf_generator-2.1.4.dist-info/METADATA
cpf_generator-2.1.4.dist-info/WHEEL
cpf_generator-2.1.4.dist-info/top_level.txt
cpf_generator-2.1.4.dist-info/RECORD
