Metadata-Version: 2.1
Name: cpf_generator
Version: 2.1.4
Summary: Generate, Validate and Format brazilian CPF
Home-page: https://github.com/matalmeida/cpf-generator
Author: Matheus Almeida
Author-email: mat.almeida@live.com
License: MIT
Platform: UNKNOWN
Classifier: Programming Language :: Python :: 3
Classifier: License :: OSI Approved :: MIT License
Classifier: Operating System :: OS Independent
